MANIFEST.in
README
setup.py
test-requirements.txt
tox.ini
cubicweb_piwik/__init__.py
cubicweb_piwik/__pkginfo__.py
cubicweb_piwik/entities.py
cubicweb_piwik/hooks.py
cubicweb_piwik/schema.py
cubicweb_piwik/site_cubicweb.py
cubicweb_piwik/views.py
cubicweb_piwik.egg-info/PKG-INFO
cubicweb_piwik.egg-info/SOURCES.txt
cubicweb_piwik.egg-info/dependency_links.txt
cubicweb_piwik.egg-info/entry_points.txt
cubicweb_piwik.egg-info/not-zip-safe
cubicweb_piwik.egg-info/requires.txt
cubicweb_piwik.egg-info/top_level.txt
cubicweb_piwik/i18n/en.po
cubicweb_piwik/i18n/es.po
cubicweb_piwik/i18n/fr.po
cubicweb_piwik/migration/postcreate.py
test/test_piwik.py
test/data/bootstrap_cubes