Metadata-Version: 1.1
Name: cubicweb-piwik
Version: 0.2.0
Summary: component to piwik trackers into the CubicWeb framework
Home-page: http://www.cubicweb.org/project/cubicweb-piwik
Author: LOGILAB S.A. (Paris, FRANCE)
Author-email: contact@logilab.fr
License: LGPL
Platform: UNKNOWN
Classifier: Environment :: Web Environment
Classifier: Framework :: CubicWeb
Classifier: Programming Language :: Python
Classifier: Programming Language :: JavaScript
